[
  {
    "time": "01:30 29/12",
    "votes": {
      "Diễn viên Nguyễn Cao Kỳ Duyên": 487866,
      "Ca sĩ Tóc Tiên": 318100,
      "Diễn viên Ninh Dương Lan Ngọc": 76244
    },
    "increase": {
      "Diễn viên Nguyễn Cao Kỳ Duyên": 37,
      "Ca sĩ Tóc Tiên": 38,
      "Diễn viên Ninh Dương Lan Ngọc": 0
    }
  },
  {
    "time": "01:45 29/12",
    "votes": {
      "Diễn viên Nguyễn Cao Kỳ Duyên": 487877,
      "Ca sĩ Tóc Tiên": 318124,
      "Diễn viên Ninh Dương Lan Ngọc": 76247
    },
    "increase": {
      "Diễn viên Nguyễn Cao Kỳ Duyên": 11,
      "Ca sĩ Tóc Tiên": 24,
      "Diễn viên Ninh Dương Lan Ngọc": 3
    }
  },
  {
    "time": "02:00 29/12",
    "votes": {
      "Diễn viên Nguyễn Cao Kỳ Duyên": 487890,
      "Ca sĩ Tóc Tiên": 318141,
      "Diễn viên Ninh Dương Lan Ngọc": 76248
    },
    "increase": {
      "Diễn viên Nguyễn Cao Kỳ Duyên": 13,
      "Ca sĩ Tóc Tiên": 17,
      "Diễn viên Ninh Dương Lan Ngọc": 1
    }
  },
  {
    "time": "02:15 29/12",
    "votes": {
      "Diễn viên Nguyễn Cao Kỳ Duyên": 487907,
      "Ca sĩ Tóc Tiên": 318156,
      "Diễn viên Ninh Dương Lan Ngọc": 76249
    },
    "increase": {
      "Diễn viên Nguyễn Cao Kỳ Duyên": 17,
      "Ca sĩ Tóc Tiên": 15,
      "Diễn viên Ninh Dương Lan Ngọc": 1
    }
  },
  {
    "time": "02:30 29/12",
    "votes": {
      "Diễn viên Nguyễn Cao Kỳ Duyên": 487928,
      "Ca sĩ Tóc Tiên": 318171,
      "Diễn viên Ninh Dương Lan Ngọc": 76249
    },
    "increase": {
      "Diễn viên Nguyễn Cao Kỳ Duyên": 21,
      "Ca sĩ Tóc Tiên": 15,
      "Diễn viên Ninh Dương Lan Ngọc": 0
    }
  },
  {
    "time": "02:45 29/12",
    "votes": {
      "Diễn viên Nguyễn Cao Kỳ Duyên": 487928,
      "Ca sĩ Tóc Tiên": 318192,
      "Diễn viên Ninh Dương Lan Ngọc": 76249
    },
    "increase": {
      "Diễn viên Nguyễn Cao Kỳ Duyên": 0,
      "Ca sĩ Tóc Tiên": 21,
      "Diễn viên Ninh Dương Lan Ngọc": 0
    }
  },
  {
    "time": "03:00 29/12",
    "votes": {
      "Diễn viên Nguyễn Cao Kỳ Duyên": 487934,
      "Ca sĩ Tóc Tiên": 318193,
      "Diễn viên Ninh Dương Lan Ngọc": 76250
    },
    "increase": {
      "Diễn viên Nguyễn Cao Kỳ Duyên": 6,
      "Ca sĩ Tóc Tiên": 1,
      "Diễn viên Ninh Dương Lan Ngọc": 1
    }
  },
  {
    "time": "03:15 29/12",
    "votes": {
      "Diễn viên Nguyễn Cao Kỳ Duyên": 487941,
      "Ca sĩ Tóc Tiên": 318206,
      "Diễn viên Ninh Dương Lan Ngọc": 76250
    },
    "increase": {
      "Diễn viên Nguyễn Cao Kỳ Duyên": 7,
      "Ca sĩ Tóc Tiên": 13,
      "Diễn viên Ninh Dương Lan Ngọc": 0
    }
  },
  {
    "time": "03:30 29/12",
    "votes": {
      "Diễn viên Nguyễn Cao Kỳ Duyên": 487943,
      "Ca sĩ Tóc Tiên": 318268,
      "Diễn viên Ninh Dương Lan Ngọc": 76266
    },
    "increase": {
      "Diễn viên Nguyễn Cao Kỳ Duyên": 2,
      "Ca sĩ Tóc Tiên": 62,
      "Diễn viên Ninh Dương Lan Ngọc": 16
    }
  },
  {
    "time": "03:45 29/12",
    "votes": {
      "Diễn viên Nguyễn Cao Kỳ Duyên": 487945,
      "Ca sĩ Tóc Tiên": 318278,
      "Diễn viên Ninh Dương Lan Ngọc": 76266
    },
    "increase": {
      "Diễn viên Nguyễn Cao Kỳ Duyên": 2,
      "Ca sĩ Tóc Tiên": 10,
      "Diễn viên Ninh Dương Lan Ngọc": 0
    }
  },
  {
    "time": "04:00 29/12",
    "votes": {
      "Diễn viên Nguyễn Cao Kỳ Duyên": 487948,
      "Ca sĩ Tóc Tiên": 318282,
      "Diễn viên Ninh Dương Lan Ngọc": 76266
    },
    "increase": {
      "Diễn viên Nguyễn Cao Kỳ Duyên": 3,
      "Ca sĩ Tóc Tiên": 4,
      "Diễn viên Ninh Dương Lan Ngọc": 0
    }
  },
  {
    "time": "04:15 29/12",
    "votes": {
      "Diễn viên Nguyễn Cao Kỳ Duyên": 487968,
      "Ca sĩ Tóc Tiên": 318283,
      "Diễn viên Ninh Dương Lan Ngọc": 76267
    },
    "increase": {
      "Diễn viên Nguyễn Cao Kỳ Duyên": 20,
      "Ca sĩ Tóc Tiên": 1,
      "Diễn viên Ninh Dương Lan Ngọc": 1
    }
  },
  {
    "time": "04:30 29/12",
    "votes": {
      "Diễn viên Nguyễn Cao Kỳ Duyên": 487978,
      "Ca sĩ Tóc Tiên": 318284,
      "Diễn viên Ninh Dương Lan Ngọc": 76267
    },
    "increase": {
      "Diễn viên Nguyễn Cao Kỳ Duyên": 10,
      "Ca sĩ Tóc Tiên": 1,
      "Diễn viên Ninh Dương Lan Ngọc": 0
    }
  },
  {
    "time": "04:45 29/12",
    "votes": {
      "Diễn viên Nguyễn Cao Kỳ Duyên": 487989,
      "Ca sĩ Tóc Tiên": 318286,
      "Diễn viên Ninh Dương Lan Ngọc": 76268
    },
    "increase": {
      "Diễn viên Nguyễn Cao Kỳ Duyên": 11,
      "Ca sĩ Tóc Tiên": 2,
      "Diễn viên Ninh Dương Lan Ngọc": 1
    }
  },
  {
    "time": "05:00 29/12",
    "votes": {
      "Diễn viên Nguyễn Cao Kỳ Duyên": 488015,
      "Ca sĩ Tóc Tiên": 318287,
      "Diễn viên Ninh Dương Lan Ngọc": 76268
    },
    "increase": {
      "Diễn viên Nguyễn Cao Kỳ Duyên": 26,
      "Ca sĩ Tóc Tiên": 1,
      "Diễn viên Ninh Dương Lan Ngọc": 0
    }
  },
  {
    "time": "05:15 29/12",
    "votes": {
      "Diễn viên Nguyễn Cao Kỳ Duyên": 488029,
      "Ca sĩ Tóc Tiên": 318287,
      "Diễn viên Ninh Dương Lan Ngọc": 76270
    },
    "increase": {
      "Diễn viên Nguyễn Cao Kỳ Duyên": 14,
      "Ca sĩ Tóc Tiên": 0,
      "Diễn viên Ninh Dương Lan Ngọc": 2
    }
  },
  {
    "time": "05:30 29/12",
    "votes": {
      "Diễn viên Nguyễn Cao Kỳ Duyên": 488045,
      "Ca sĩ Tóc Tiên": 318289,
      "Diễn viên Ninh Dương Lan Ngọc": 76270
    },
    "increase": {
      "Diễn viên Nguyễn Cao Kỳ Duyên": 16,
      "Ca sĩ Tóc Tiên": 2,
      "Diễn viên Ninh Dương Lan Ngọc": 0
    }
  },
  {
    "time": "05:45 29/12",
    "votes": {
      "Diễn viên Nguyễn Cao Kỳ Duyên": 488059,
      "Ca sĩ Tóc Tiên": 318291,
      "Diễn viên Ninh Dương Lan Ngọc": 76270
    },
    "increase": {
      "Diễn viên Nguyễn Cao Kỳ Duyên": 14,
      "Ca sĩ Tóc Tiên": 2,
      "Diễn viên Ninh Dương Lan Ngọc": 0
    }
  },
  {
    "time": "06:00 29/12",
    "votes": {
      "Diễn viên Nguyễn Cao Kỳ Duyên": 488074,
      "Ca sĩ Tóc Tiên": 318293,
      "Diễn viên Ninh Dương Lan Ngọc": 76270
    },
    "increase": {
      "Diễn viên Nguyễn Cao Kỳ Duyên": 15,
      "Ca sĩ Tóc Tiên": 2,
      "Diễn viên Ninh Dương Lan Ngọc": 0
    }
  },
  {
    "time": "06:15 29/12",
    "votes": {
      "Diễn viên Nguyễn Cao Kỳ Duyên": 488097,
      "Ca sĩ Tóc Tiên": 318299,
      "Diễn viên Ninh Dương Lan Ngọc": 76271
    },
    "increase": {
      "Diễn viên Nguyễn Cao Kỳ Duyên": 23,
      "Ca sĩ Tóc Tiên": 6,
      "Diễn viên Ninh Dương Lan Ngọc": 1
    }
  },
  {
    "time": "06:30 29/12",
    "votes": {
      "Diễn viên Nguyễn Cao Kỳ Duyên": 488129,
      "Ca sĩ Tóc Tiên": 318309,
      "Diễn viên Ninh Dương Lan Ngọc": 76273
    },
    "increase": {
      "Diễn viên Nguyễn Cao Kỳ Duyên": 32,
      "Ca sĩ Tóc Tiên": 10,
      "Diễn viên Ninh Dương Lan Ngọc": 2
    }
  },
  {
    "time": "06:45 29/12",
    "votes": {
      "Diễn viên Nguyễn Cao Kỳ Duyên": 488153,
      "Ca sĩ Tóc Tiên": 318322,
      "Diễn viên Ninh Dương Lan Ngọc": 76273
    },
    "increase": {
      "Diễn viên Nguyễn Cao Kỳ Duyên": 24,
      "Ca sĩ Tóc Tiên": 13,
      "Diễn viên Ninh Dương Lan Ngọc": 0
    }
  },
  {
    "time": "07:00 29/12",
    "votes": {
      "Diễn viên Nguyễn Cao Kỳ Duyên": 488187,
      "Ca sĩ Tóc Tiên": 318336,
      "Diễn viên Ninh Dương Lan Ngọc": 76274
    },
    "increase": {
      "Diễn viên Nguyễn Cao Kỳ Duyên": 34,
      "Ca sĩ Tóc Tiên": 14,
      "Diễn viên Ninh Dương Lan Ngọc": 1
    }
  },
  {
    "time": "07:15 29/12",
    "votes": {
      "Diễn viên Nguyễn Cao Kỳ Duyên": 488219,
      "Ca sĩ Tóc Tiên": 318343,
      "Diễn viên Ninh Dương Lan Ngọc": 76274
    },
    "increase": {
      "Diễn viên Nguyễn Cao Kỳ Duyên": 32,
      "Ca sĩ Tóc Tiên": 7,
      "Diễn viên Ninh Dương Lan Ngọc": 0
    }
  },
  {
    "time": "07:30 29/12",
    "votes": {
      "Diễn viên Nguyễn Cao Kỳ Duyên": 488246,
      "Ca sĩ Tóc Tiên": 318376,
      "Diễn viên Ninh Dương Lan Ngọc": 76274
    },
    "increase": {
      "Diễn viên Nguyễn Cao Kỳ Duyên": 27,
      "Ca sĩ Tóc Tiên": 33,
      "Diễn viên Ninh Dương Lan Ngọc": 0
    }
  },
  {
    "time": "07:45 29/12",
    "votes": {
      "Diễn viên Nguyễn Cao Kỳ Duyên": 488315,
      "Ca sĩ Tóc Tiên": 318400,
      "Diễn viên Ninh Dương Lan Ngọc": 76276
    },
    "increase": {
      "Diễn viên Nguyễn Cao Kỳ Duyên": 69,
      "Ca sĩ Tóc Tiên": 24,
      "Diễn viên Ninh Dương Lan Ngọc": 2
    }
  },
  {
    "time": "08:00 29/12",
    "votes": {
      "Diễn viên Nguyễn Cao Kỳ Duyên": 488395,
      "Ca sĩ Tóc Tiên": 318434,
      "Diễn viên Ninh Dương Lan Ngọc": 76279
    },
    "increase": {
      "Diễn viên Nguyễn Cao Kỳ Duyên": 80,
      "Ca sĩ Tóc Tiên": 34,
      "Diễn viên Ninh Dương Lan Ngọc": 3
    }
  },
  {
    "time": "08:15 29/12",
    "votes": {
      "Diễn viên Nguyễn Cao Kỳ Duyên": 488479,
      "Ca sĩ Tóc Tiên": 318454,
      "Diễn viên Ninh Dương Lan Ngọc": 76280
    },
    "increase": {
      "Diễn viên Nguyễn Cao Kỳ Duyên": 84,
      "Ca sĩ Tóc Tiên": 20,
      "Diễn viên Ninh Dương Lan Ngọc": 1
    }
  },
  {
    "time": "08:30 29/12",
    "votes": {
      "Diễn viên Nguyễn Cao Kỳ Duyên": 488565,
      "Ca sĩ Tóc Tiên": 318476,
      "Diễn viên Ninh Dương Lan Ngọc": 76300
    },
    "increase": {
      "Diễn viên Nguyễn Cao Kỳ Duyên": 86,
      "Ca sĩ Tóc Tiên": 22,
      "Diễn viên Ninh Dương Lan Ngọc": 20
    }
  },
  {
    "time": "08:45 29/12",
    "votes": {
      "Diễn viên Nguyễn Cao Kỳ Duyên": 488671,
      "Ca sĩ Tóc Tiên": 318496,
      "Diễn viên Ninh Dương Lan Ngọc": 76324
    },
    "increase": {
      "Diễn viên Nguyễn Cao Kỳ Duyên": 106,
      "Ca sĩ Tóc Tiên": 20,
      "Diễn viên Ninh Dương Lan Ngọc": 24
    }
  },
  {
    "time": "09:00 29/12",
    "votes": {
      "Diễn viên Nguyễn Cao Kỳ Duyên": 488774,
      "Ca sĩ Tóc Tiên": 318564,
      "Diễn viên Ninh Dương Lan Ngọc": 76344
    },
    "increase": {
      "Diễn viên Nguyễn Cao Kỳ Duyên": 103,
      "Ca sĩ Tóc Tiên": 68,
      "Diễn viên Ninh Dương Lan Ngọc": 20
    }
  },
  {
    "time": "09:15 29/12",
    "votes": {
      "Diễn viên Nguyễn Cao Kỳ Duyên": 488862,
      "Ca sĩ Tóc Tiên": 318611,
      "Diễn viên Ninh Dương Lan Ngọc": 76360
    },
    "increase": {
      "Diễn viên Nguyễn Cao Kỳ Duyên": 88,
      "Ca sĩ Tóc Tiên": 47,
      "Diễn viên Ninh Dương Lan Ngọc": 16
    }
  },
  {
    "time": "09:30 29/12",
    "votes": {
      "Diễn viên Nguyễn Cao Kỳ Duyên": 488958,
      "Ca sĩ Tóc Tiên": 318683,
      "Diễn viên Ninh Dương Lan Ngọc": 76405
    },
    "increase": {
      "Diễn viên Nguyễn Cao Kỳ Duyên": 96,
      "Ca sĩ Tóc Tiên": 72,
      "Diễn viên Ninh Dương Lan Ngọc": 45
    }
  },
  {
    "time": "09:45 29/12",
    "votes": {
      "Diễn viên Nguyễn Cao Kỳ Duyên": 489324,
      "Ca sĩ Tóc Tiên": 318761,
      "Diễn viên Ninh Dương Lan Ngọc": 76473
    },
    "increase": {
      "Diễn viên Nguyễn Cao Kỳ Duyên": 366,
      "Ca sĩ Tóc Tiên": 78,
      "Diễn viên Ninh Dương Lan Ngọc": 68
    }
  },
  {
    "time": "10:00 29/12",
    "votes": {
      "Diễn viên Nguyễn Cao Kỳ Duyên": 489388,
      "Ca sĩ Tóc Tiên": 318834,
      "Diễn viên Ninh Dương Lan Ngọc": 76511
    },
    "increase": {
      "Diễn viên Nguyễn Cao Kỳ Duyên": 64,
      "Ca sĩ Tóc Tiên": 73,
      "Diễn viên Ninh Dương Lan Ngọc": 38
    }
  },
  {
    "time": "10:15 29/12",
    "votes": {
      "Diễn viên Nguyễn Cao Kỳ Duyên": 489708,
      "Ca sĩ Tóc Tiên": 318900,
      "Diễn viên Ninh Dương Lan Ngọc": 76545
    },
    "increase": {
      "Diễn viên Nguyễn Cao Kỳ Duyên": 320,
      "Ca sĩ Tóc Tiên": 66,
      "Diễn viên Ninh Dương Lan Ngọc": 34
    }
  },
  {
    "time": "10:30 29/12",
    "votes": {
      "Diễn viên Nguyễn Cao Kỳ Duyên": 489764,
      "Ca sĩ Tóc Tiên": 318953,
      "Diễn viên Ninh Dương Lan Ngọc": 76624
    },
    "increase": {
      "Diễn viên Nguyễn Cao Kỳ Duyên": 56,
      "Ca sĩ Tóc Tiên": 53,
      "Diễn viên Ninh Dương Lan Ngọc": 79
    }
  },
  {
    "time": "10:45 29/12",
    "votes": {
      "Diễn viên Nguyễn Cao Kỳ Duyên": 489828,
      "Ca sĩ Tóc Tiên": 319008,
      "Diễn viên Ninh Dương Lan Ngọc": 76690
    },
    "increase": {
      "Diễn viên Nguyễn Cao Kỳ Duyên": 64,
      "Ca sĩ Tóc Tiên": 55,
      "Diễn viên Ninh Dương Lan Ngọc": 66
    }
  },
  {
    "time": "11:00 29/12",
    "votes": {
      "Diễn viên Nguyễn Cao Kỳ Duyên": 489905,
      "Ca sĩ Tóc Tiên": 319079,
      "Diễn viên Ninh Dương Lan Ngọc": 76775
    },
    "increase": {
      "Diễn viên Nguyễn Cao Kỳ Duyên": 77,
      "Ca sĩ Tóc Tiên": 71,
      "Diễn viên Ninh Dương Lan Ngọc": 85
    }
  },
  {
    "time": "11:15 29/12",
    "votes": {
      "Diễn viên Nguyễn Cao Kỳ Duyên": 490561,
      "Ca sĩ Tóc Tiên": 319169,
      "Diễn viên Ninh Dương Lan Ngọc": 76904
    },
    "increase": {
      "Diễn viên Nguyễn Cao Kỳ Duyên": 656,
      "Ca sĩ Tóc Tiên": 90,
      "Diễn viên Ninh Dương Lan Ngọc": 129
    }
  },
  {
    "time": "11:30 29/12",
    "votes": {
      "Diễn viên Nguyễn Cao Kỳ Duyên": 490637,
      "Ca sĩ Tóc Tiên": 319231,
      "Diễn viên Ninh Dương Lan Ngọc": 76962
    },
    "increase": {
      "Diễn viên Nguyễn Cao Kỳ Duyên": 76,
      "Ca sĩ Tóc Tiên": 62,
      "Diễn viên Ninh Dương Lan Ngọc": 58
    }
  },
  {
    "time": "11:45 29/12",
    "votes": {
      "Diễn viên Nguyễn Cao Kỳ Duyên": 490718,
      "Ca sĩ Tóc Tiên": 319330,
      "Diễn viên Ninh Dương Lan Ngọc": 77030
    },
    "increase": {
      "Diễn viên Nguyễn Cao Kỳ Duyên": 81,
      "Ca sĩ Tóc Tiên": 99,
      "Diễn viên Ninh Dương Lan Ngọc": 68
    }
  },
  {
    "time": "12:00 29/12",
    "votes": {
      "Diễn viên Nguyễn Cao Kỳ Duyên": 490804,
      "Ca sĩ Tóc Tiên": 319999,
      "Diễn viên Ninh Dương Lan Ngọc": 77116
    },
    "increase": {
      "Diễn viên Nguyễn Cao Kỳ Duyên": 86,
      "Ca sĩ Tóc Tiên": 669,
      "Diễn viên Ninh Dương Lan Ngọc": 86
    }
  },
  {
    "time": "12:15 29/12",
    "votes": {
      "Diễn viên Nguyễn Cao Kỳ Duyên": 490854,
      "Ca sĩ Tóc Tiên": 322216,
      "Diễn viên Ninh Dương Lan Ngọc": 77173
    },
    "increase": {
      "Diễn viên Nguyễn Cao Kỳ Duyên": 50,
      "Ca sĩ Tóc Tiên": 2217,
      "Diễn viên Ninh Dương Lan Ngọc": 57
    }
  },
  {
    "time": "12:30 29/12",
    "votes": {
      "Diễn viên Nguyễn Cao Kỳ Duyên": 490906,
      "Ca sĩ Tóc Tiên": 322284,
      "Diễn viên Ninh Dương Lan Ngọc": 77233
    },
    "increase": {
      "Diễn viên Nguyễn Cao Kỳ Duyên": 52,
      "Ca sĩ Tóc Tiên": 68,
      "Diễn viên Ninh Dương Lan Ngọc": 60
    }
  },
  {
    "time": "12:45 29/12",
    "votes": {
      "Diễn viên Nguyễn Cao Kỳ Duyên": 490970,
      "Ca sĩ Tóc Tiên": 322372,
      "Diễn viên Ninh Dương Lan Ngọc": 77330
    },
    "increase": {
      "Diễn viên Nguyễn Cao Kỳ Duyên": 64,
      "Ca sĩ Tóc Tiên": 88,
      "Diễn viên Ninh Dương Lan Ngọc": 97
    }
  },
  {
    "time": "13:00 29/12",
    "votes": {
      "Diễn viên Nguyễn Cao Kỳ Duyên": 491361,
      "Ca sĩ Tóc Tiên": 322461,
      "Diễn viên Ninh Dương Lan Ngọc": 77428
    },
    "increase": {
      "Diễn viên Nguyễn Cao Kỳ Duyên": 391,
      "Ca sĩ Tóc Tiên": 89,
      "Diễn viên Ninh Dương Lan Ngọc": 98
    }
  },
  {
    "time": "13:15 29/12",
    "votes": {
      "Diễn viên Nguyễn Cao Kỳ Duyên": 491409,
      "Ca sĩ Tóc Tiên": 322531,
      "Diễn viên Ninh Dương Lan Ngọc": 77572
    },
    "increase": {
      "Diễn viên Nguyễn Cao Kỳ Duyên": 48,
      "Ca sĩ Tóc Tiên": 70,
      "Diễn viên Ninh Dương Lan Ngọc": 144
    }
  },
  {
    "time": "13:30 29/12",
    "votes": {
      "Diễn viên Nguyễn Cao Kỳ Duyên": 491451,
      "Ca sĩ Tóc Tiên": 322612,
      "Diễn viên Ninh Dương Lan Ngọc": 77681
    },
    "increase": {
      "Diễn viên Nguyễn Cao Kỳ Duyên": 42,
      "Ca sĩ Tóc Tiên": 81,
      "Diễn viên Ninh Dương Lan Ngọc": 109
    }
  },
  {
    "time": "13:45 29/12",
    "votes": {
      "Diễn viên Nguyễn Cao Kỳ Duyên": 491503,
      "Ca sĩ Tóc Tiên": 322683,
      "Diễn viên Ninh Dương Lan Ngọc": 77806
    },
    "increase": {
      "Diễn viên Nguyễn Cao Kỳ Duyên": 52,
      "Ca sĩ Tóc Tiên": 71,
      "Diễn viên Ninh Dương Lan Ngọc": 125
    }
  },
  {
    "time": "14:00 29/12",
    "votes": {
      "Diễn viên Nguyễn Cao Kỳ Duyên": 491553,
      "Ca sĩ Tóc Tiên": 322757,
      "Diễn viên Ninh Dương Lan Ngọc": 77901
    },
    "increase": {
      "Diễn viên Nguyễn Cao Kỳ Duyên": 50,
      "Ca sĩ Tóc Tiên": 74,
      "Diễn viên Ninh Dương Lan Ngọc": 95
    }
  },
  {
    "time": "14:15 29/12",
    "votes": {
      "Diễn viên Nguyễn Cao Kỳ Duyên": 491598,
      "Ca sĩ Tóc Tiên": 322830,
      "Diễn viên Ninh Dương Lan Ngọc": 77986
    },
    "increase": {
      "Diễn viên Nguyễn Cao Kỳ Duyên": 45,
      "Ca sĩ Tóc Tiên": 73,
      "Diễn viên Ninh Dương Lan Ngọc": 85
    }
  },
  {
    "time": "14:30 29/12",
    "votes": {
      "Diễn viên Nguyễn Cao Kỳ Duyên": 491640,
      "Ca sĩ Tóc Tiên": 322896,
      "Diễn viên Ninh Dương Lan Ngọc": 78079
    },
    "increase": {
      "Diễn viên Nguyễn Cao Kỳ Duyên": 42,
      "Ca sĩ Tóc Tiên": 66,
      "Diễn viên Ninh Dương Lan Ngọc": 93
    }
  },
  {
    "time": "14:45 29/12",
    "votes": {
      "Diễn viên Nguyễn Cao Kỳ Duyên": 491682,
      "Ca sĩ Tóc Tiên": 322988,
      "Diễn viên Ninh Dương Lan Ngọc": 78148
    },
    "increase": {
      "Diễn viên Nguyễn Cao Kỳ Duyên": 42,
      "Ca sĩ Tóc Tiên": 92,
      "Diễn viên Ninh Dương Lan Ngọc": 69
    }
  },
  {
    "time": "15:00 29/12",
    "votes": {
      "Diễn viên Nguyễn Cao Kỳ Duyên": 491704,
      "Ca sĩ Tóc Tiên": 323048,
      "Diễn viên Ninh Dương Lan Ngọc": 78225
    },
    "increase": {
      "Diễn viên Nguyễn Cao Kỳ Duyên": 22,
      "Ca sĩ Tóc Tiên": 60,
      "Diễn viên Ninh Dương Lan Ngọc": 77
    }
  },
  {
    "time": "15:15 29/12",
    "votes": {
      "Diễn viên Nguyễn Cao Kỳ Duyên": 491748,
      "Ca sĩ Tóc Tiên": 323129,
      "Diễn viên Ninh Dương Lan Ngọc": 78288
    },
    "increase": {
      "Diễn viên Nguyễn Cao Kỳ Duyên": 44,
      "Ca sĩ Tóc Tiên": 81,
      "Diễn viên Ninh Dương Lan Ngọc": 63
    }
  },
  {
    "time": "15:30 29/12",
    "votes": {
      "Diễn viên Nguyễn Cao Kỳ Duyên": 491766,
      "Ca sĩ Tóc Tiên": 323212,
      "Diễn viên Ninh Dương Lan Ngọc": 78389
    },
    "increase": {
      "Diễn viên Nguyễn Cao Kỳ Duyên": 18,
      "Ca sĩ Tóc Tiên": 83,
      "Diễn viên Ninh Dương Lan Ngọc": 101
    }
  },
  {
    "time": "15:45 29/12",
    "votes": {
      "Diễn viên Nguyễn Cao Kỳ Duyên": 491793,
      "Ca sĩ Tóc Tiên": 323300,
      "Diễn viên Ninh Dương Lan Ngọc": 78506
    },
    "increase": {
      "Diễn viên Nguyễn Cao Kỳ Duyên": 27,
      "Ca sĩ Tóc Tiên": 88,
      "Diễn viên Ninh Dương Lan Ngọc": 117
    }
  },
  {
    "time": "16:00 29/12",
    "votes": {
      "Diễn viên Nguyễn Cao Kỳ Duyên": 491845,
      "Ca sĩ Tóc Tiên": 323424,
      "Diễn viên Ninh Dương Lan Ngọc": 78605
    },
    "increase": {
      "Diễn viên Nguyễn Cao Kỳ Duyên": 52,
      "Ca sĩ Tóc Tiên": 124,
      "Diễn viên Ninh Dương Lan Ngọc": 99
    }
  },
  {
    "time": "16:15 29/12",
    "votes": {
      "Diễn viên Nguyễn Cao Kỳ Duyên": 491891,
      "Ca sĩ Tóc Tiên": 323528,
      "Diễn viên Ninh Dương Lan Ngọc": 78669
    },
    "increase": {
      "Diễn viên Nguyễn Cao Kỳ Duyên": 46,
      "Ca sĩ Tóc Tiên": 104,
      "Diễn viên Ninh Dương Lan Ngọc": 64
    }
  },
  {
    "time": "16:30 29/12",
    "votes": {
      "Diễn viên Nguyễn Cao Kỳ Duyên": 491941,
      "Ca sĩ Tóc Tiên": 323641,
      "Diễn viên Ninh Dương Lan Ngọc": 78738
    },
    "increase": {
      "Diễn viên Nguyễn Cao Kỳ Duyên": 50,
      "Ca sĩ Tóc Tiên": 113,
      "Diễn viên Ninh Dương Lan Ngọc": 69
    }
  },
  {
    "time": "16:45 29/12",
    "votes": {
      "Diễn viên Nguyễn Cao Kỳ Duyên": 491986,
      "Ca sĩ Tóc Tiên": 323747,
      "Diễn viên Ninh Dương Lan Ngọc": 78795
    },
    "increase": {
      "Diễn viên Nguyễn Cao Kỳ Duyên": 45,
      "Ca sĩ Tóc Tiên": 106,
      "Diễn viên Ninh Dương Lan Ngọc": 57
    }
  },
  {
    "time": "17:00 29/12",
    "votes": {
      "Diễn viên Nguyễn Cao Kỳ Duyên": 492035,
      "Ca sĩ Tóc Tiên": 323865,
      "Diễn viên Ninh Dương Lan Ngọc": 78876
    },
    "increase": {
      "Diễn viên Nguyễn Cao Kỳ Duyên": 49,
      "Ca sĩ Tóc Tiên": 118,
      "Diễn viên Ninh Dương Lan Ngọc": 81
    }
  },
  {
    "time": "17:15 29/12",
    "votes": {
      "Diễn viên Nguyễn Cao Kỳ Duyên": 492074,
      "Ca sĩ Tóc Tiên": 323952,
      "Diễn viên Ninh Dương Lan Ngọc": 78945
    },
    "increase": {
      "Diễn viên Nguyễn Cao Kỳ Duyên": 39,
      "Ca sĩ Tóc Tiên": 87,
      "Diễn viên Ninh Dương Lan Ngọc": 69
    }
  },
  {
    "time": "17:30 29/12",
    "votes": {
      "Diễn viên Nguyễn Cao Kỳ Duyên": 492121,
      "Ca sĩ Tóc Tiên": 324032,
      "Diễn viên Ninh Dương Lan Ngọc": 79026
    },
    "increase": {
      "Diễn viên Nguyễn Cao Kỳ Duyên": 47,
      "Ca sĩ Tóc Tiên": 80,
      "Diễn viên Ninh Dương Lan Ngọc": 81
    }
  },
  {
    "time": "17:45 29/12",
    "votes": {
      "Diễn viên Nguyễn Cao Kỳ Duyên": 492170,
      "Ca sĩ Tóc Tiên": 324083,
      "Diễn viên Ninh Dương Lan Ngọc": 79134
    },
    "increase": {
      "Diễn viên Nguyễn Cao Kỳ Duyên": 49,
      "Ca sĩ Tóc Tiên": 51,
      "Diễn viên Ninh Dương Lan Ngọc": 108
    }
  },
  {
    "time": "18:00 29/12",
    "votes": {
      "Diễn viên Nguyễn Cao Kỳ Duyên": 492241,
      "Ca sĩ Tóc Tiên": 324113,
      "Diễn viên Ninh Dương Lan Ngọc": 79224
    },
    "increase": {
      "Diễn viên Nguyễn Cao Kỳ Duyên": 71,
      "Ca sĩ Tóc Tiên": 30,
      "Diễn viên Ninh Dương Lan Ngọc": 90
    }
  },
  {
    "time": "18:15 29/12",
    "votes": {
      "Diễn viên Nguyễn Cao Kỳ Duyên": 492344,
      "Ca sĩ Tóc Tiên": 324151,
      "Diễn viên Ninh Dương Lan Ngọc": 79298
    },
    "increase": {
      "Diễn viên Nguyễn Cao Kỳ Duyên": 103,
      "Ca sĩ Tóc Tiên": 38,
      "Diễn viên Ninh Dương Lan Ngọc": 74
    }
  },
  {
    "time": "18:30 29/12",
    "votes": {
      "Diễn viên Nguyễn Cao Kỳ Duyên": 492406,
      "Ca sĩ Tóc Tiên": 324204,
      "Diễn viên Ninh Dương Lan Ngọc": 79373
    },
    "increase": {
      "Diễn viên Nguyễn Cao Kỳ Duyên": 62,
      "Ca sĩ Tóc Tiên": 53,
      "Diễn viên Ninh Dương Lan Ngọc": 75
    }
  },
  {
    "time": "18:45 29/12",
    "votes": {
      "Diễn viên Nguyễn Cao Kỳ Duyên": 492466,
      "Ca sĩ Tóc Tiên": 324241,
      "Diễn viên Ninh Dương Lan Ngọc": 79420
    },
    "increase": {
      "Diễn viên Nguyễn Cao Kỳ Duyên": 60,
      "Ca sĩ Tóc Tiên": 37,
      "Diễn viên Ninh Dương Lan Ngọc": 47
    }
  },
  {
    "time": "19:00 29/12",
    "votes": {
      "Diễn viên Nguyễn Cao Kỳ Duyên": 492543,
      "Ca sĩ Tóc Tiên": 324279,
      "Diễn viên Ninh Dương Lan Ngọc": 79487
    },
    "increase": {
      "Diễn viên Nguyễn Cao Kỳ Duyên": 77,
      "Ca sĩ Tóc Tiên": 38,
      "Diễn viên Ninh Dương Lan Ngọc": 67
    }
  },
  {
    "time": "19:15 29/12",
    "votes": {
      "Diễn viên Nguyễn Cao Kỳ Duyên": 492601,
      "Ca sĩ Tóc Tiên": 324319,
      "Diễn viên Ninh Dương Lan Ngọc": 79578
    },
    "increase": {
      "Diễn viên Nguyễn Cao Kỳ Duyên": 58,
      "Ca sĩ Tóc Tiên": 40,
      "Diễn viên Ninh Dương Lan Ngọc": 91
    }
  },
  {
    "time": "19:30 29/12",
    "votes": {
      "Diễn viên Nguyễn Cao Kỳ Duyên": 492660,
      "Ca sĩ Tóc Tiên": 324382,
      "Diễn viên Ninh Dương Lan Ngọc": 79707
    },
    "increase": {
      "Diễn viên Nguyễn Cao Kỳ Duyên": 59,
      "Ca sĩ Tóc Tiên": 63,
      "Diễn viên Ninh Dương Lan Ngọc": 129
    }
  },
  {
    "time": "19:45 29/12",
    "votes": {
      "Diễn viên Nguyễn Cao Kỳ Duyên": 492706,
      "Ca sĩ Tóc Tiên": 324492,
      "Diễn viên Ninh Dương Lan Ngọc": 79829
    },
    "increase": {
      "Diễn viên Nguyễn Cao Kỳ Duyên": 46,
      "Ca sĩ Tóc Tiên": 110,
      "Diễn viên Ninh Dương Lan Ngọc": 122
    }
  },
  {
    "time": "20:00 29/12",
    "votes": {
      "Diễn viên Nguyễn Cao Kỳ Duyên": 492760,
      "Ca sĩ Tóc Tiên": 324600,
      "Diễn viên Ninh Dương Lan Ngọc": 79962
    },
    "increase": {
      "Diễn viên Nguyễn Cao Kỳ Duyên": 54,
      "Ca sĩ Tóc Tiên": 108,
      "Diễn viên Ninh Dương Lan Ngọc": 133
    }
  },
  {
    "time": "20:15 29/12",
    "votes": {
      "Diễn viên Nguyễn Cao Kỳ Duyên": 492805,
      "Ca sĩ Tóc Tiên": 324690,
      "Diễn viên Ninh Dương Lan Ngọc": 80044
    },
    "increase": {
      "Diễn viên Nguyễn Cao Kỳ Duyên": 45,
      "Ca sĩ Tóc Tiên": 90,
      "Diễn viên Ninh Dương Lan Ngọc": 82
    }
  },
  {
    "time": "20:30 29/12",
    "votes": {
      "Diễn viên Nguyễn Cao Kỳ Duyên": 492857,
      "Ca sĩ Tóc Tiên": 324794,
      "Diễn viên Ninh Dương Lan Ngọc": 80099
    },
    "increase": {
      "Diễn viên Nguyễn Cao Kỳ Duyên": 52,
      "Ca sĩ Tóc Tiên": 104,
      "Diễn viên Ninh Dương Lan Ngọc": 55
    }
  },
  {
    "time": "20:45 29/12",
    "votes": {
      "Diễn viên Nguyễn Cao Kỳ Duyên": 492914,
      "Ca sĩ Tóc Tiên": 324888,
      "Diễn viên Ninh Dương Lan Ngọc": 80159
    },
    "increase": {
      "Diễn viên Nguyễn Cao Kỳ Duyên": 57,
      "Ca sĩ Tóc Tiên": 94,
      "Diễn viên Ninh Dương Lan Ngọc": 60
    }
  },
  {
    "time": "21:00 29/12",
    "votes": {
      "Diễn viên Nguyễn Cao Kỳ Duyên": 492976,
      "Ca sĩ Tóc Tiên": 325014,
      "Diễn viên Ninh Dương Lan Ngọc": 80238
    },
    "increase": {
      "Diễn viên Nguyễn Cao Kỳ Duyên": 62,
      "Ca sĩ Tóc Tiên": 126,
      "Diễn viên Ninh Dương Lan Ngọc": 79
    }
  },
  {
    "time": "21:15 29/12",
    "votes": {
      "Diễn viên Nguyễn Cao Kỳ Duyên": 493027,
      "Ca sĩ Tóc Tiên": 325140,
      "Diễn viên Ninh Dương Lan Ngọc": 80325
    },
    "increase": {
      "Diễn viên Nguyễn Cao Kỳ Duyên": 51,
      "Ca sĩ Tóc Tiên": 126,
      "Diễn viên Ninh Dương Lan Ngọc": 87
    }
  },
  {
    "time": "21:30 29/12",
    "votes": {
      "Diễn viên Nguyễn Cao Kỳ Duyên": 493087,
      "Ca sĩ Tóc Tiên": 325914,
      "Diễn viên Ninh Dương Lan Ngọc": 80422
    },
    "increase": {
      "Diễn viên Nguyễn Cao Kỳ Duyên": 60,
      "Ca sĩ Tóc Tiên": 774,
      "Diễn viên Ninh Dương Lan Ngọc": 97
    }
  },
  {
    "time": "21:45 29/12",
    "votes": {
      "Diễn viên Nguyễn Cao Kỳ Duyên": 493214,
      "Ca sĩ Tóc Tiên": 326109,
      "Diễn viên Ninh Dương Lan Ngọc": 80543
    },
    "increase": {
      "Diễn viên Nguyễn Cao Kỳ Duyên": 127,
      "Ca sĩ Tóc Tiên": 195,
      "Diễn viên Ninh Dương Lan Ngọc": 121
    }
  },
  {
    "time": "22:00 29/12",
    "votes": {
      "Diễn viên Nguyễn Cao Kỳ Duyên": 493317,
      "Ca sĩ Tóc Tiên": 326315,
      "Diễn viên Ninh Dương Lan Ngọc": 80658
    },
    "increase": {
      "Diễn viên Nguyễn Cao Kỳ Duyên": 103,
      "Ca sĩ Tóc Tiên": 206,
      "Diễn viên Ninh Dương Lan Ngọc": 115
    }
  },
  {
    "time": "22:15 29/12",
    "votes": {
      "Diễn viên Nguyễn Cao Kỳ Duyên": 493388,
      "Ca sĩ Tóc Tiên": 326469,
      "Diễn viên Ninh Dương Lan Ngọc": 80762
    },
    "increase": {
      "Diễn viên Nguyễn Cao Kỳ Duyên": 71,
      "Ca sĩ Tóc Tiên": 154,
      "Diễn viên Ninh Dương Lan Ngọc": 104
    }
  },
  {
    "time": "22:30 29/12",
    "votes": {
      "Diễn viên Nguyễn Cao Kỳ Duyên": 493497,
      "Ca sĩ Tóc Tiên": 326604,
      "Diễn viên Ninh Dương Lan Ngọc": 80902
    },
    "increase": {
      "Diễn viên Nguyễn Cao Kỳ Duyên": 109,
      "Ca sĩ Tóc Tiên": 135,
      "Diễn viên Ninh Dương Lan Ngọc": 140
    }
  },
  {
    "time": "22:45 29/12",
    "votes": {
      "Diễn viên Nguyễn Cao Kỳ Duyên": 493580,
      "Ca sĩ Tóc Tiên": 326738,
      "Diễn viên Ninh Dương Lan Ngọc": 81058
    },
    "increase": {
      "Diễn viên Nguyễn Cao Kỳ Duyên": 83,
      "Ca sĩ Tóc Tiên": 134,
      "Diễn viên Ninh Dương Lan Ngọc": 156
    }
  },
  {
    "time": "23:00 29/12",
    "votes": {
      "Diễn viên Nguyễn Cao Kỳ Duyên": 493652,
      "Ca sĩ Tóc Tiên": 326904,
      "Diễn viên Ninh Dương Lan Ngọc": 81213
    },
    "increase": {
      "Diễn viên Nguyễn Cao Kỳ Duyên": 72,
      "Ca sĩ Tóc Tiên": 166,
      "Diễn viên Ninh Dương Lan Ngọc": 155
    }
  },
  {
    "time": "23:15 29/12",
    "votes": {
      "Diễn viên Nguyễn Cao Kỳ Duyên": 493712,
      "Ca sĩ Tóc Tiên": 327075,
      "Diễn viên Ninh Dương Lan Ngọc": 81398
    },
    "increase": {
      "Diễn viên Nguyễn Cao Kỳ Duyên": 60,
      "Ca sĩ Tóc Tiên": 171,
      "Diễn viên Ninh Dương Lan Ngọc": 185
    }
  },
  {
    "time": "23:30 29/12",
    "votes": {
      "Diễn viên Nguyễn Cao Kỳ Duyên": 493763,
      "Ca sĩ Tóc Tiên": 327220,
      "Diễn viên Ninh Dương Lan Ngọc": 81557
    },
    "increase": {
      "Diễn viên Nguyễn Cao Kỳ Duyên": 51,
      "Ca sĩ Tóc Tiên": 145,
      "Diễn viên Ninh Dương Lan Ngọc": 159
    }
  },
  {
    "time": "23:45 29/12",
    "votes": {
      "Diễn viên Nguyễn Cao Kỳ Duyên": 493795,
      "Ca sĩ Tóc Tiên": 327487,
      "Diễn viên Ninh Dương Lan Ngọc": 81659
    },
    "increase": {
      "Diễn viên Nguyễn Cao Kỳ Duyên": 32,
      "Ca sĩ Tóc Tiên": 267,
      "Diễn viên Ninh Dương Lan Ngọc": 102
    }
  },
  {
    "time": "00:00 30/12",
    "votes": {
      "Diễn viên Nguyễn Cao Kỳ Duyên": 493833,
      "Ca sĩ Tóc Tiên": 327579,
      "Diễn viên Ninh Dương Lan Ngọc": 81705
    },
    "increase": {
      "Diễn viên Nguyễn Cao Kỳ Duyên": 38,
      "Ca sĩ Tóc Tiên": 92,
      "Diễn viên Ninh Dương Lan Ngọc": 46
    }
  },
  {
    "time": "00:15 30/12",
    "votes": {
      "Diễn viên Nguyễn Cao Kỳ Duyên": 493879,
      "Ca sĩ Tóc Tiên": 327613,
      "Diễn viên Ninh Dương Lan Ngọc": 81708
    },
    "increase": {
      "Diễn viên Nguyễn Cao Kỳ Duyên": 46,
      "Ca sĩ Tóc Tiên": 34,
      "Diễn viên Ninh Dương Lan Ngọc": 3
    }
  },
  {
    "time": "00:30 30/12",
    "votes": {
      "Diễn viên Nguyễn Cao Kỳ Duyên": 493926,
      "Ca sĩ Tóc Tiên": 327637,
      "Diễn viên Ninh Dương Lan Ngọc": 81711
    },
    "increase": {
      "Diễn viên Nguyễn Cao Kỳ Duyên": 47,
      "Ca sĩ Tóc Tiên": 24,
      "Diễn viên Ninh Dương Lan Ngọc": 3
    }
  },
  {
    "time": "00:45 30/12",
    "votes": {
      "Diễn viên Nguyễn Cao Kỳ Duyên": 493984,
      "Ca sĩ Tóc Tiên": 327657,
      "Diễn viên Ninh Dương Lan Ngọc": 81720
    },
    "increase": {
      "Diễn viên Nguyễn Cao Kỳ Duyên": 58,
      "Ca sĩ Tóc Tiên": 20,
      "Diễn viên Ninh Dương Lan Ngọc": 9
    }
  },
  {
    "time": "01:00 30/12",
    "votes": {
      "Diễn viên Nguyễn Cao Kỳ Duyên": 494024,
      "Ca sĩ Tóc Tiên": 327683,
      "Diễn viên Ninh Dương Lan Ngọc": 81720
    },
    "increase": {
      "Diễn viên Nguyễn Cao Kỳ Duyên": 40,
      "Ca sĩ Tóc Tiên": 26,
      "Diễn viên Ninh Dương Lan Ngọc": 0
    }
  },
  {
    "time": "01:15 30/12",
    "votes": {
      "Diễn viên Nguyễn Cao Kỳ Duyên": 494066,
      "Ca sĩ Tóc Tiên": 327702,
      "Diễn viên Ninh Dương Lan Ngọc": 81721
    },
    "increase": {
      "Diễn viên Nguyễn Cao Kỳ Duyên": 42,
      "Ca sĩ Tóc Tiên": 19,
      "Diễn viên Ninh Dương Lan Ngọc": 1
    }
  },
  {
    "time": "01:30 30/12",
    "votes": {
      "Diễn viên Nguyễn Cao Kỳ Duyên": 494103,
      "Ca sĩ Tóc Tiên": 327723,
      "Diễn viên Ninh Dương Lan Ngọc": 81722
    },
    "increase": {
      "Diễn viên Nguyễn Cao Kỳ Duyên": 37,
      "Ca sĩ Tóc Tiên": 21,
      "Diễn viên Ninh Dương Lan Ngọc": 1
    }
  },
  {
    "time": "01:45 30/12",
    "votes": {
      "Diễn viên Nguyễn Cao Kỳ Duyên": 494140,
      "Ca sĩ Tóc Tiên": 327730,
      "Diễn viên Ninh Dương Lan Ngọc": 81725
    },
    "increase": {
      "Diễn viên Nguyễn Cao Kỳ Duyên": 37,
      "Ca sĩ Tóc Tiên": 7,
      "Diễn viên Ninh Dương Lan Ngọc": 3
    }
  },
  {
    "time": "02:00 30/12",
    "votes": {
      "Diễn viên Nguyễn Cao Kỳ Duyên": 494167,
      "Ca sĩ Tóc Tiên": 327751,
      "Diễn viên Ninh Dương Lan Ngọc": 81725
    },
    "increase": {
      "Diễn viên Nguyễn Cao Kỳ Duyên": 27,
      "Ca sĩ Tóc Tiên": 21,
      "Diễn viên Ninh Dương Lan Ngọc": 0
    }
  },
  {
    "time": "02:15 30/12",
    "votes": {
      "Diễn viên Nguyễn Cao Kỳ Duyên": 494191,
      "Ca sĩ Tóc Tiên": 327770,
      "Diễn viên Ninh Dương Lan Ngọc": 81725
    },
    "increase": {
      "Diễn viên Nguyễn Cao Kỳ Duyên": 24,
      "Ca sĩ Tóc Tiên": 19,
      "Diễn viên Ninh Dương Lan Ngọc": 0
    }
  }
]